amazon_braket_build_tools-0.2.14.dist-info/licenses/LICENSE
amazon_braket_build_tools-0.2.14.dist-info/licenses/NOTICE
braket/_build_tools/_version.py
braket/flake8_plugins/braket_checkstyle_plugin.py
amazon_braket_build_tools-0.2.14.dist-info/METADATA
amazon_braket_build_tools-0.2.14.dist-info/WHEEL
amazon_braket_build_tools-0.2.14.dist-info/entry_points.txt
amazon_braket_build_tools-0.2.14.dist-info/top_level.txt
amazon_braket_build_tools-0.2.14.dist-info/RECORD
