Metadata-Version: 2.4
Name: amazon-braket-build-tools
Version: 0.2.14
Summary: A set of build tools for Amazon Braket
Home-page: https://github.com/aws/amazon-braket-build-tools
Author: Amazon Web Services
License: Apache License 2.0
Keywords: Amazon AWS Quantum
Classifier: Development Status :: 2 - Pre-Alpha
Classifier: Intended Audience :: Developers
Classifier: Natural Language :: English
Classifier: License :: OSI Approved :: Apache Software License
Classifier: Programming Language :: Python
Classifier: Programming Language :: Python :: 3.9
Classifier: Programming Language :: Python :: 3.10
Classifier: Programming Language :: Python :: 3.11
Requires-Python: >= 3.8
License-File: LICENSE
License-File: NOTICE
Requires-Dist: flake8
Provides-Extra: test
Requires-Dist: black; extra == "test"
Requires-Dist: coverage; extra == "test"
Requires-Dist: isort; extra == "test"
Requires-Dist: pre-commit; extra == "test"
Requires-Dist: pytest; extra == "test"
Requires-Dist: pytest-benchmark; extra == "test"
Requires-Dist: pytest-cov; extra == "test"
Requires-Dist: pytest-rerunfailures; extra == "test"
Requires-Dist: pytest-xdist; extra == "test"
Requires-Dist: sphinx; extra == "test"
Requires-Dist: sphinx-rtd-theme; extra == "test"
Requires-Dist: sphinxcontrib-apidoc; extra == "test"
Requires-Dist: tox; extra == "test"
Dynamic: author
Dynamic: classifier
Dynamic: description
Dynamic: description-content-type
Dynamic: home-page
Dynamic: keywords
Dynamic: license
Dynamic: license-file
Dynamic: provides-extra
Dynamic: requires-dist
Dynamic: requires-python
Dynamic: summary
